{
  "verse": "त्वं भज हिरण्यगर्भं त्वमपि हरं त्वञ्च तत्परं ब्रह्म । विनिहितकृष्णानंदामहन्तु वृन्दाटवीं वन्दे ॥",
  "words": {
    "त्वं": "You",
    "भज": "worship",
    "हिरण्यगर्भं": {
      "हिरण्य": "gold",
      "गर्भं": "womb"
    },
    "त्वमपि": "You also",
    "हरं": "Hari (Vishnu)",
    "त्वञ्च": "and You",
    "तत्परं": "the ultimate",
    "ब्रह्म": "Brahman",
    "विनिहित": "established",
    "कृष्णानंदा": {
      "कृष्णा": "Krishna",
      "आनंदा": "bliss"
    },
    "महन्तु": "may bestow",
    "वृन्दाटवीं": "to the grove of Vrindavan",
    "वन्दे": "I salute"
  },
  "overall_meaning": "I salute You, worshiping the golden-wombed Hiranyagarbha, You who are also Hari (Vishnu), and You who are the ultimate Brahman. May the bliss of Krishna bestow blessings upon the grove of Vrindavan."
}
