{
    "verse_no": "७-२५-२",
    "verse": "अथात आत्मादेश एवात्मैवाधस्तादात्मोपरिष्टादात्मा पश्चादात्मा पुरस्तादात्मा दक्षिणत आत्मोत्तरत आत्मैवेद सर्वमिति स वा एष एवं पश्यन्नेवं मन्वान एवं विजानन्नात्मरतिरात्मक्रीड आत्ममिथुन आत्मानन्दः स स्वराड्भवति तस्य सर्वेषु लोकेषु कामचारो भवति अथ येऽन्यथाऽतो विदुरन्यराजानस्ते क्षय्यलोका भवन्ति तेषा सर्वेषु लोकेष्वकामचारो भवति॥",
    "terms": {
        "अथात्": "Now",
        "आत्मादेश": "self, soul + person",
        "एव": "indeed",
        "आत्मैव": "the self alone",
        "अधस्ताद्": "below, beneath",
        "आत्मा": "self",
        "उपरिष्टात्": "above, over, superior",
        "पश्चात्": "behind, after",
        "पुरस्तात्": "in front, before",
        "दक्षिणत्": "to the right",
        "उत्तरतः": "to the left",
        "एद्": "this",
        "सर्वम्": "everything",
        "इति": "thus",
        "स": "he",
        "वा": "or",
        "एषः": "this",
        "एवं": "in this way",
        "पश्यन्": "seeing",
        "मन्वान्": "thinking",
        "विजानन्": "knowing",
        "आत्मरतिः": "one who delights in the self",
        "आत्मक्रीडः": "one who enjoys in the self",
        "आत्ममिथुनः": "one who is united with the self",
        "आत्मानन्दः": "one who finds joy in the self",
        "सः": "that person",
        "स्वराड्भवति": "becomes self-satisfied",
        "तस्य": "for him",
        "सर्वेषु": "in all",
        "लोकेषु": "worlds",
        "कामचारः": "free from desire",
        "भवति": "becomes",
        "अथ": "then",
        "ये": "those who",
        "अन्यथा": "otherwise",
        "अतः": "therefore",
        "विदुः": "they know",
        "अन्यराजानः": "other rulers",
        "ते": "they",
        "क्षय्यलोकाः": "destroyable worlds",
        "भवन्ति": "become",
        "तेषा": "for them",
        "अकामचारः": "with desire",
        "Meaning: Now, the self alone is below the self, above the self, behind the self, in front of the self, to the right of the self, and to the left of the self. Indeed, he sees everything as the self alone. In this way, thinking and knowing, one who delights in the self, enjoys in the self, is united with the self, and finds joy in the self, becomes self": "satisfied. For such a person, desires cease in all worlds. On the other hand, those who do not know this, other rulers, their worlds become destructible. For them, desires arise in all worlds."
    },
    "meaning": "",

    "ref": [
        "kamana aur upasana 2 274"
    ]
}