{
    "verse_no": "१-२-५",
    "verse": "स ऐक्षत यदि वा इममभिमस्ये कनीयोऽन्नं करिष्य इति। स तया वाचा तेनात्मनेद सर्वमसृजत यदिदं किंचर्चो यजूषि सामानि छन्दासि यज्ञान्प्रजाः पशून्। स यद्यदेवासृजत तत्तदत्तुमध्रियत। सर्वं वा अत्तीति तददितेरदितित्व सर्वस्येतसात्ता भवति सर्वमस्यान्नं भवति य एवमेतददितेरदितित्वं वेद॥",
    "terms": {
        "सः ऐक्षत": "He saw",
        "यदि": "if",
        "वा": "or",
        "इमम्": "this",
        "अभिमस्ये": "I shall consume",
        "कनीयः": "smaller",
        "अन्नं": "the food",
        "करिष्ये": "I shall make",
        "इति": "thus",
        "सः तया वाचा": "he with that speech",
        "तेन": "by it",
        "आत्मनेत्": "himself",
        "सर्वम्": "everything",
        "असृजत्": "created",
        "इदं": "this",
        "किञ्चित्": "little",
        "छो": "a part",
        "यजूषि": "in the Rigveda",
        "सावानि": "in the Samaveda",
        "छन्दांसि": "in the verses",
        "यज्ञानि": "in the sacrifices",
        "प्रजाः": "living beings",
        "पशून्": "animals",
        "सः यद्यद्": "he who created",
        "देवाः": "gods",
        "आसृजत्": "created",
        "तत्": "that",
        "तद्": "that",
        "अत्तुम्": "to eat",
        "अध्रियत्": "did not dare",
        "अत्ति": "eats",
        "अदिति": "Aditi",
        "ईतिः": "the world",
        "सर्वस्य": "of everything",
        "एतसा": "through this",
        "आत्ता": "the eater",
        "भवति": "becomes",
        "सर्वमस्य": "of everything",
        "यः": "he who",
        "एवम्": "thus",
        "एतत्": "this",
        "वेद": "knows"
    },
    "meaning": "Meaning:He saw if I shall consume this smaller food or I shall make it bigger. With that speech, he himself created everything, including a little part in the Rigveda, Samaveda, and the verses and sacrifices, as well as living beings and animals. He who created the gods did not dare to eat what he created. Everything eats that, and Aditi is the eater of everything. Everything becomes the food for everything, and he who knows Aditi thus knows the world."
}